{
    "path": "flat-bg.vert",
    "precisions": { "int": "mediump", "float": "lowp"},
    "attributes": [
        {
            "name": "aPosition",
            "type": "vec3",
            "aliases": ["vertexPosition"]
        }
    ],
    "blocks": [],
    "outputs": [
        { "name": "rayDir", "type": "vec3" }
    ],
    "uniforms": [
        { "name": "uView", "type": "mat4", "aliases": ["view", "u_View", "viewMatrix"] },
        { "name": "uProjection", "type": "mat4", "aliases": ["projection", "u_Projection", "projectionMatrix"]  }
    ],
    "structs": []
}